mcp_server_airoom/__init__.py
mcp_server_airoom/__main__.py
mcp_server_airoom-0.4.1.dist-info/METADATA
mcp_server_airoom-0.4.1.dist-info/WHEEL
mcp_server_airoom-0.4.1.dist-info/entry_points.txt
mcp_server_airoom-0.4.1.dist-info/top_level.txt
mcp_server_airoom-0.4.1.dist-info/RECORD
